octoprint_plugin_tool/__init__.py
octoprint_plugin_tool-0.1.0.dist-info/licenses/LICENSE.txt
octoprint_plugin_tool-0.1.0.dist-info/METADATA
octoprint_plugin_tool-0.1.0.dist-info/WHEEL
octoprint_plugin_tool-0.1.0.dist-info/entry_points.txt
octoprint_plugin_tool-0.1.0.dist-info/top_level.txt
octoprint_plugin_tool-0.1.0.dist-info/RECORD
