Metadata-Version: 2.4
Name: octoprint-plugin-tool
Version: 0.1.0
Summary: A CLI tool to help with maintaining OctoPrint Plugins
Author-email: Gina Häußge <gina@octoprint.org>
Maintainer-email: Gina Häußge <gina@octoprint.org>
License-Expression: AGPL-3.0-or-later
Project-URL: homepage, https://github.com/OctoPrint/octoprint-plugin-tool/
Project-URL: issues, https://github.com/OctoPrint/octoprint-plugin-tool/issues
Project-URL: source, https://github.com/OctoPrint/octoprint-plugin-tool/
Requires-Python: >=3.9
License-File: LICENSE.txt
Requires-Dist: deepmerge>=2.0
Requires-Dist: packaging>=24.2
Requires-Dist: pyyaml
Requires-Dist: validate-pyproject
Requires-Dist: tomli>=1.1.0; python_version < "3.11"
Requires-Dist: tomli-w
Provides-Extra: develop
Requires-Dist: pytest; extra == "develop"
Requires-Dist: pre-commit; extra == "develop"
Dynamic: license-file
